pyscada/__init__.py
pyscada/webservice/__init__.py
pyscada/webservice/admin.py
pyscada/webservice/apps.py
pyscada/webservice/device.py
pyscada/webservice/models.py
pyscada/webservice/signals.py
pyscada/webservice/worker.py
pyscada/webservice/devices/__init__.py
pyscada/webservice/devices/enedis.py
pyscada/webservice/migrations/0001_initial.py
pyscada/webservice/migrations/0002_auto_20200902_0940.py
pyscada/webservice/migrations/0003_add_device_protocol.py
pyscada/webservice/migrations/0004_auto_20200902_1027.py
pyscada/webservice/migrations/0005_webservicevariable_path.py
pyscada/webservice/migrations/0006_auto_20200902_1328.py
pyscada/webservice/migrations/0007_auto_20200903_1340.py
pyscada/webservice/migrations/0008_webserviceaction_active.py
pyscada/webservice/migrations/0009_auto_20200904_1042.py
pyscada/webservice/migrations/0010_auto_20200907_0958.py
pyscada/webservice/migrations/0011_auto_20200907_1021.py
pyscada/webservice/migrations/0012_auto_20200910_0706.py
pyscada/webservice/migrations/0013_webservicedevice_http_proxy.py
pyscada/webservice/migrations/0014_webserviceaction_webservice_content_type.py
pyscada/webservice/migrations/0015_auto_20201209_1133.py
pyscada/webservice/migrations/0016_auto_20201209_1133.py
pyscada/webservice/migrations/0017_auto_20211203_2025.py
pyscada/webservice/migrations/0018_webserviceaction_payload.py
pyscada/webservice/migrations/0019_auto_20211203_2300.py
pyscada/webservice/migrations/0020_auto_20220105_1000.py
pyscada/webservice/migrations/__init__.py
pyscada_webservice-0.8.0.dist-info/AUTHORS
pyscada_webservice-0.8.0.dist-info/LICENSE
pyscada_webservice-0.8.0.dist-info/METADATA
pyscada_webservice-0.8.0.dist-info/WHEEL
pyscada_webservice-0.8.0.dist-info/top_level.txt
pyscada_webservice-0.8.0.dist-info/RECORD
